{
  "content": [
    {
      "transactionId": 171314,
      "account": {
        "accountId": 305,
        "accountClosingDate": null,
        "accountOpeningDate": 1184040000000,
        "accountType": {
          "accountTypeId": 16,
          "accountType": "VIRTUAL_WALLET_RESERVE",
          "active": "Y",
          "description": "PNC Virtual Wallet Reserve (Interest Checking)",
          "interestRate": null,
          "annualPercentageRate": null,
          "creditLimit": 6
        },
        "accountNumber": "12488057354529",
        "alterDate": 1184040000000,
        "balance": 1000,
        "businessUnit": {
          "businessUnitId": 1,
          "address": "1736 East Carson Street, Pittsburgh, PA",
          "bank": {
            "bankId": 1,
            "bankName": "PNC",
            "bankRegNumber": "10310080",
            "country": "USA",
            "registeredAddress": "1 PNC Plaza, 249 5th Ave, Pittsburgh, PA 15222",
            "routingNumber": "031000053"
          },
          "unitName": "PNC South Side"
        },
        "isJointAccount": "N",
        "isOnlineAccessEnabled": "Y",
        "status": "ACTIVE",
        "version": 0
      },
      "balance": 1025,
      "counterPartyAccount": {
        "accountId": 592,
        "accountClosingDate": null,
        "accountOpeningDate": 1241928000000,
        "accountType": {
          "accountTypeId": 15,
          "accountType": "VIRTUAL_WALLET_SPEND",
          "active": "Y",
          "description": "PNC Virtual Wallet Spend (Checking)",
          "interestRate": null,
          "annualPercentageRate": null,
          "creditLimit": 0
        },
        "accountNumber": "13436013555667",
        "alterDate": 1241928000000,
        "balance": 1000,
        "businessUnit": {
          "businessUnitId": 1,
          "address": "1736 East Carson Street, Pittsburgh, PA",
          "bank": {
            "bankId": 1,
            "bankName": "PNC",
            "bankRegNumber": "10310080",
            "country": "USA",
            "registeredAddress": "1 PNC Plaza, 249 5th Ave, Pittsburgh, PA 15222",
            "routingNumber": "031000053"
          },
          "unitName": "PNC South Side"
        },
        "isJointAccount": "N",
        "isOnlineAccessEnabled": "Y",
        "status": "ACTIVE",
        "version": 442
      },
      "method": "CREDIT",
      "amount": 25,
      "transactionDate": 1388638800000,
      "transactionType": {
        "transactionTypeId": 1,
        "accountType": "ATM",
        "active": "Y",
        "description": "Deposit or withdraw funds using an ATM."
      },
      "mccCode": {
        "mccCode": 5533,
        "editedDescription": "Automotive Parts, Accessories Stores",
        "combinedDescription": "Automotive Parts, Accessories Stores",
        "usdaDescription": "Automotive Parts, Accessories Stores",
        "irsDescription": "Automotive",
        "irsReportable": "No1.6041-3(c)"
      },
      "comments": "ATM Credit",
      "currency": {
        "currencyCode": "USD",
        "active": "Y",
        "alterDate": 1486875600000,
        "description": "United States Dollar",
        "symbol": "USD",
        "digitsAfterDecimal": 2,
        "currencySymbolPosition": "BEFORE_NUMBER"
      },
      "longitude": -77.01416,
      "latitude": 40.637925
    },
    {
      "transactionId": 171325,
      "account": {
        "accountId": 305,
        "accountClosingDate": null,
        "accountOpeningDate": 1184040000000,
        "accountType": {
          "accountTypeId": 16,
          "accountType": "VIRTUAL_WALLET_RESERVE",
          "active": "Y",
          "description": "PNC Virtual Wallet Reserve (Interest Checking)",
          "interestRate": null,
          "annualPercentageRate": null,
          "creditLimit": 6
        },
        "accountNumber": "12488057354529",
        "alterDate": 1184040000000,
        "balance": 1000,
        "businessUnit": {
          "businessUnitId": 1,
          "address": "1736 East Carson Street, Pittsburgh, PA",
          "bank": {
            "bankId": 1,
            "bankName": "PNC",
            "bankRegNumber": "10310080",
            "country": "USA",
            "registeredAddress": "1 PNC Plaza, 249 5th Ave, Pittsburgh, PA 15222",
            "routingNumber": "031000053"
          },
          "unitName": "PNC South Side"
        },
        "isJointAccount": "N",
        "isOnlineAccessEnabled": "Y",
        "status": "ACTIVE",
        "version": 0
      },
      "balance": 1090,
      "counterPartyAccount": {
        "accountId": 733,
        "accountClosingDate": null,
        "accountOpeningDate": 1234760400000,
        "accountType": {
          "accountTypeId": 1,
          "accountType": "STANDARD_SAVINGS",
          "active": "Y",
          "description": "Standard Savings",
          "interestRate": 12,
          "annualPercentageRate": 0,
          "creditLimit": 0
        },
        "accountNumber": "45666049426969",
        "alterDate": 1246334400000,
        "balance": 2500,
        "businessUnit": {
          "businessUnitId": 8,
          "address": "600 Grant Street, Pittsburgh, PA",
          "bank": {
            "bankId": 1,
            "bankName": "PNC",
            "bankRegNumber": "10310080",
            "country": "USA",
            "registeredAddress": "1 PNC Plaza, 249 5th Ave, Pittsburgh, PA 15222",
            "routingNumber": "031000053"
          },
          "unitName": "PNC Steel Plaza"
        },
        "isJointAccount": "N",
        "isOnlineAccessEnabled": "Y",
        "status": "ACTIVE",
        "version": 2929
      },
      "method": "CREDIT",
      "amount": 65,
      "transactionDate": 1388984400000,
      "transactionType": {
        "transactionTypeId": 1,
        "accountType": "ATM",
        "active": "Y",
        "description": "Deposit or withdraw funds using an ATM."
      },
      "mccCode": {
        "mccCode": 5732,
        "editedDescription": "Electronic Sales",
        "combinedDescription": "Electronic Sales",
        "usdaDescription": "Electronic Sales",
        "irsDescription": "Electronics/General Merchandise",
        "irsReportable": "No1.6041-3(c)"
      },
      "comments": "ATM Credit",
      "currency": {
        "currencyCode": "USD",
        "active": "Y",
        "alterDate": 1486875600000,
        "description": "United States Dollar",
        "symbol": "USD",
        "digitsAfterDecimal": 2,
        "currencySymbolPosition": "BEFORE_NUMBER"
      },
      "longitude": -80.073853,
      "latitude": 40.478031
    },
    {
      "transactionId": 171326,
      "account": {
        "accountId": 305,
        "accountClosingDate": null,
        "accountOpeningDate": 1184040000000,
        "accountType": {
          "accountTypeId": 16,
          "accountType": "VIRTUAL_WALLET_RESERVE",
          "active": "Y",
          "description": "PNC Virtual Wallet Reserve (Interest Checking)",
          "interestRate": null,
          "annualPercentageRate": null,
          "creditLimit": 6
        },
        "accountNumber": "12488057354529",
        "alterDate": 1184040000000,
        "balance": 1000,
        "businessUnit": {
          "businessUnitId": 1,
          "address": "1736 East Carson Street, Pittsburgh, PA",
          "bank": {
            "bankId": 1,
            "bankName": "PNC",
            "bankRegNumber": "10310080",
            "country": "USA",
            "registeredAddress": "1 PNC Plaza, 249 5th Ave, Pittsburgh, PA 15222",
            "routingNumber": "031000053"
          },
          "unitName": "PNC South Side"
        },
        "isJointAccount": "N",
        "isOnlineAccessEnabled": "Y",
        "status": "ACTIVE",
        "version": 0
      },
      "balance": 1215.5,
      "counterPartyAccount": {
        "accountId": 50,
        "accountClosingDate": null,
        "accountOpeningDate": 1235451600000,
        "accountType": {
          "accountTypeId": 5,
          "accountType": "INTEREST_CHECKING",
          "active": "Y",
          "description": "Interest Checking",
          "interestRate": 6,
          "annualPercentageRate": 0,
          "creditLimit": 0
        },
        "accountNumber": "83984068247194",
        "alterDate": 1241928000000,
        "balance": 5000,
        "businessUnit": {
          "businessUnitId": 1,
          "address": "1736 East Carson Street, Pittsburgh, PA",
          "bank": {
            "bankId": 1,
            "bankName": "PNC",
            "bankRegNumber": "10310080",
            "country": "USA",
            "registeredAddress": "1 PNC Plaza, 249 5th Ave, Pittsburgh, PA 15222",
            "routingNumber": "031000053"
          },
          "unitName": "PNC South Side"
        },
        "isJointAccount": "N",
        "isOnlineAccessEnabled": "Y",
        "status": "ACTIVE",
        "version": 911
      },
      "method": "CREDIT",
      "amount": 125.5,
      "transactionDate": 1388984400000,
      "transactionType": {
        "transactionTypeId": 1,
        "accountType": "ATM",
        "active": "Y",
        "description": "Deposit or withdraw funds using an ATM."
      },
      "mccCode": {
        "mccCode": 5411,
        "editedDescription": "Grocery Stores, Supermarkets",
        "combinedDescription": "Grocery Stores, Supermarkets",
        "usdaDescription": "Grocery Stores",
        "irsDescription": "Groceries",
        "irsReportable": "No1.6041-3(c)"
      },
      "comments": "ATM Credit",
      "currency": {
        "currencyCode": "USD",
        "active": "Y",
        "alterDate": 1486875600000,
        "description": "United States Dollar",
        "symbol": "USD",
        "digitsAfterDecimal": 2,
        "currencySymbolPosition": "BEFORE_NUMBER"
      },
      "longitude": -87.874146,
      "latitude": 41.91633
    },
    {
      "transactionId": 171340,
      "account": {
        "accountId": 305,
        "accountClosingDate": null,
        "accountOpeningDate": 1184040000000,
        "accountType": {
          "accountTypeId": 16,
          "accountType": "VIRTUAL_WALLET_RESERVE",
          "active": "Y",
          "description": "PNC Virtual Wallet Reserve (Interest Checking)",
          "interestRate": null,
          "annualPercentageRate": null,
          "creditLimit": 6
        },
        "accountNumber": "12488057354529",
        "alterDate": 1184040000000,
        "balance": 1000,
        "businessUnit": {
          "businessUnitId": 1,
          "address": "1736 East Carson Street, Pittsburgh, PA",
          "bank": {
            "bankId": 1,
            "bankName": "PNC",
            "bankRegNumber": "10310080",
            "country": "USA",
            "registeredAddress": "1 PNC Plaza, 249 5th Ave, Pittsburgh, PA 15222",
            "routingNumber": "031000053"
          },
          "unitName": "PNC South Side"
        },
        "isJointAccount": "N",
        "isOnlineAccessEnabled": "Y",
        "status": "ACTIVE",
        "version": 0
      },
      "balance": 1212,
      "counterPartyAccount": {
        "accountId": 612,
        "accountClosingDate": null,
        "accountOpeningDate": 1254283200000,
        "accountType": {
          "accountTypeId": 17,
          "accountType": "VIRTUAL_WALLET_GROWTH",
          "active": "Y",
          "description": "PNC Virtual Wallet Growth (Savings)",
          "interestRate": null,
          "annualPercentageRate": null,
          "creditLimit": 10
        },
        "accountNumber": "49676088314835",
        "alterDate": 1254283200000,
        "balance": 1000,
        "businessUnit": {
          "businessUnitId": 4,
          "address": "5810 Forbes Avenue, Pittsburgh, PA",
          "bank": {
            "bankId": 1,
            "bankName": "PNC",
            "bankRegNumber": "10310080",
            "country": "USA",
            "registeredAddress": "1 PNC Plaza, 249 5th Ave, Pittsburgh, PA 15222",
            "routingNumber": "031000053"
          },
          "unitName": "PNC Squirrel Hill"
        },
        "isJointAccount": "N",
        "isOnlineAccessEnabled": "Y",
        "status": "ACTIVE",
        "version": 0
      },
      "method": "DEBIT",
      "amount": 3.5,
      "transactionDate": 1389502800000,
      "transactionType": {
        "transactionTypeId": 5,
        "accountType": "WITHDRAWAL",
        "active": "Y",
        "description": "Deduct funds from an account by any method."
      },
      "mccCode": {
        "mccCode": 5814,
        "editedDescription": "Fast Food Restaurants",
        "combinedDescription": "Fast Food Restaurants",
        "usdaDescription": "Fast Food Restaurants",
        "irsDescription": "Restaurants",
        "irsReportable": "No1.6041-3(c)"
      },
      "comments": "WITHDRAWAL",
      "currency": {
        "currencyCode": "USD",
        "active": "Y",
        "alterDate": 1486875600000,
        "description": "United States Dollar",
        "symbol": "USD",
        "digitsAfterDecimal": 2,
        "currencySymbolPosition": "BEFORE_NUMBER"
      },
      "longitude": -75.687561,
      "latitude": 39.120339
    },
    {
      "transactionId": 171352,
      "account": {
        "accountId": 305,
        "accountClosingDate": null,
        "accountOpeningDate": 1184040000000,
        "accountType": {
          "accountTypeId": 16,
          "accountType": "VIRTUAL_WALLET_RESERVE",
          "active": "Y",
          "description": "PNC Virtual Wallet Reserve (Interest Checking)",
          "interestRate": null,
          "annualPercentageRate": null,
          "creditLimit": 6
        },
        "accountNumber": "12488057354529",
        "alterDate": 1184040000000,
        "balance": 1000,
        "businessUnit": {
          "businessUnitId": 1,
          "address": "1736 East Carson Street, Pittsburgh, PA",
          "bank": {
            "bankId": 1,
            "bankName": "PNC",
            "bankRegNumber": "10310080",
            "country": "USA",
            "registeredAddress": "1 PNC Plaza, 249 5th Ave, Pittsburgh, PA 15222",
            "routingNumber": "031000053"
          },
          "unitName": "PNC South Side"
        },
        "isJointAccount": "N",
        "isOnlineAccessEnabled": "Y",
        "status": "ACTIVE",
        "version": 0
      },
      "balance": 1289,
      "counterPartyAccount": {
        "accountId": 221,
        "accountClosingDate": null,
        "accountOpeningDate": 1254283200000,
        "accountType": {
          "accountTypeId": 16,
          "accountType": "VIRTUAL_WALLET_RESERVE",
          "active": "Y",
          "description": "PNC Virtual Wallet Reserve (Interest Checking)",
          "interestRate": null,
          "annualPercentageRate": null,
          "creditLimit": 6
        },
        "accountNumber": "33336032689757",
        "alterDate": 1254283200000,
        "balance": 1000,
        "businessUnit": {
          "businessUnitId": 4,
          "address": "5810 Forbes Avenue, Pittsburgh, PA",
          "bank": {
            "bankId": 1,
            "bankName": "PNC",
            "bankRegNumber": "10310080",
            "country": "USA",
            "registeredAddress": "1 PNC Plaza, 249 5th Ave, Pittsburgh, PA 15222",
            "routingNumber": "031000053"
          },
          "unitName": "PNC Squirrel Hill"
        },
        "isJointAccount": "N",
        "isOnlineAccessEnabled": "Y",
        "status": "ACTIVE",
        "version": 0
      },
      "method": "CREDIT",
      "amount": 77,
      "transactionDate": 1389934800000,
      "transactionType": {
        "transactionTypeId": 1,
        "accountType": "ATM",
        "active": "Y",
        "description": "Deposit or withdraw funds using an ATM."
      },
      "mccCode": {
        "mccCode": 5912,
        "editedDescription": "Drug Stores and Pharmacies",
        "combinedDescription": "Drug Stores and Pharmacies",
        "usdaDescription": "Drug Stores and Pharmacies",
        "irsDescription": "Healthcare/Medical",
        "irsReportable": "No1.6041-3(c)"
      },
      "comments": "ATM Credit",
      "currency": {
        "currencyCode": "USD",
        "active": "Y",
        "alterDate": 1486875600000,
        "description": "United States Dollar",
        "symbol": "USD",
        "digitsAfterDecimal": 2,
        "currencySymbolPosition": "BEFORE_NUMBER"
      },
      "longitude": -82.998794,
      "latitude": 39.961176
    },
    {
      "transactionId": 171358,
      "account": {
        "accountId": 305,
        "accountClosingDate": null,
        "accountOpeningDate": 1184040000000,
        "accountType": {
          "accountTypeId": 16,
          "accountType": "VIRTUAL_WALLET_RESERVE",
          "active": "Y",
          "description": "PNC Virtual Wallet Reserve (Interest Checking)",
          "interestRate": null,
          "annualPercentageRate": null,
          "creditLimit": 6
        },
        "accountNumber": "12488057354529",
        "alterDate": 1184040000000,
        "balance": 1000,
        "businessUnit": {
          "businessUnitId": 1,
          "address": "1736 East Carson Street, Pittsburgh, PA",
          "bank": {
            "bankId": 1,
            "bankName": "PNC",
            "bankRegNumber": "10310080",
            "country": "USA",
            "registeredAddress": "1 PNC Plaza, 249 5th Ave, Pittsburgh, PA 15222",
            "routingNumber": "031000053"
          },
          "unitName": "PNC South Side"
        },
        "isJointAccount": "N",
        "isOnlineAccessEnabled": "Y",
        "status": "ACTIVE",
        "version": 0
      },
      "balance": 1336.5,
      "counterPartyAccount": {
        "accountId": 482,
        "accountClosingDate": null,
        "accountOpeningDate": 1167973200000,
        "accountType": {
          "accountTypeId": 2,
          "accountType": "STANDARD_CHECKING",
          "active": "Y",
          "description": "Standard Checking",
          "interestRate": 12,
          "annualPercentageRate": 0,
          "creditLimit": 0
        },
        "accountNumber": "63323074618625",
        "alterDate": 1184040000000,
        "balance": 5000,
        "businessUnit": {
          "businessUnitId": 1,
          "address": "1736 East Carson Street, Pittsburgh, PA",
          "bank": {
            "bankId": 1,
            "bankName": "PNC",
            "bankRegNumber": "10310080",
            "country": "USA",
            "registeredAddress": "1 PNC Plaza, 249 5th Ave, Pittsburgh, PA 15222",
            "routingNumber": "031000053"
          },
          "unitName": "PNC South Side"
        },
        "isJointAccount": "N",
        "isOnlineAccessEnabled": "Y",
        "status": "ACTIVE",
        "version": 812
      },
      "method": "CREDIT",
      "amount": 47.5,
      "transactionDate": 1390107600000,
      "transactionType": {
        "transactionTypeId": 1,
        "accountType": "ATM",
        "active": "Y",
        "description": "Deposit or withdraw funds using an ATM."
      },
      "mccCode": {
        "mccCode": 5942,
        "editedDescription": "Book Stores",
        "combinedDescription": "Book Stores",
        "usdaDescription": "Book Stores",
        "irsDescription": "Book Stores",
        "irsReportable": "No1.6041-3(c)"
      },
      "comments": "ATM Credit",
      "currency": {
        "currencyCode": "USD",
        "active": "Y",
        "alterDate": 1486875600000,
        "description": "United States Dollar",
        "symbol": "USD",
        "digitsAfterDecimal": 2,
        "currencySymbolPosition": "BEFORE_NUMBER"
      },
      "longitude": -74.005941,
      "latitude": 40.712784
    },
    {
      "transactionId": 171359,
      "account": {
        "accountId": 305,
        "accountClosingDate": null,
        "accountOpeningDate": 1184040000000,
        "accountType": {
          "accountTypeId": 16,
          "accountType": "VIRTUAL_WALLET_RESERVE",
          "active": "Y",
          "description": "PNC Virtual Wallet Reserve (Interest Checking)",
          "interestRate": null,
          "annualPercentageRate": null,
          "creditLimit": 6
        },
        "accountNumber": "12488057354529",
        "alterDate": 1184040000000,
        "balance": 1000,
        "businessUnit": {
          "businessUnitId": 1,
          "address": "1736 East Carson Street, Pittsburgh, PA",
          "bank": {
            "bankId": 1,
            "bankName": "PNC",
            "bankRegNumber": "10310080",
            "country": "USA",
            "registeredAddress": "1 PNC Plaza, 249 5th Ave, Pittsburgh, PA 15222",
            "routingNumber": "031000053"
          },
          "unitName": "PNC South Side"
        },
        "isJointAccount": "N",
        "isOnlineAccessEnabled": "Y",
        "status": "ACTIVE",
        "version": 0
      },
      "balance": 1354.5,
      "counterPartyAccount": {
        "accountId": 558,
        "accountClosingDate": null,
        "accountOpeningDate": 1246334400000,
        "accountType": {
          "accountTypeId": 17,
          "accountType": "VIRTUAL_WALLET_GROWTH",
          "active": "Y",
          "description": "PNC Virtual Wallet Growth (Savings)",
          "interestRate": null,
          "annualPercentageRate": null,
          "creditLimit": 10
        },
        "accountNumber": "97475079343572",
        "alterDate": 1246334400000,
        "balance": 1000,
        "businessUnit": {
          "businessUnitId": 8,
          "address": "600 Grant Street, Pittsburgh, PA",
          "bank": {
            "bankId": 1,
            "bankName": "PNC",
            "bankRegNumber": "10310080",
            "country": "USA",
            "registeredAddress": "1 PNC Plaza, 249 5th Ave, Pittsburgh, PA 15222",
            "routingNumber": "031000053"
          },
          "unitName": "PNC Steel Plaza"
        },
        "isJointAccount": "N",
        "isOnlineAccessEnabled": "Y",
        "status": "ACTIVE",
        "version": 0
      },
      "method": "CREDIT",
      "amount": 18,
      "transactionDate": 1390194000000,
      "transactionType": {
        "transactionTypeId": 4,
        "accountType": "DEPOSIT",
        "active": "Y",
        "description": "Add funds to an account by any method."
      },
      "mccCode": {
        "mccCode": 5651,
        "editedDescription": "Family Clothing Stores",
        "combinedDescription": "Family Clothing Stores",
        "usdaDescription": "Family Clothing Stores",
        "irsDescription": "Personal/Family",
        "irsReportable": "No1.6041-3(c)"
      },
      "comments": "DEPOSIT",
      "currency": {
        "currencyCode": "USD",
        "active": "Y",
        "alterDate": 1486875600000,
        "description": "United States Dollar",
        "symbol": "USD",
        "digitsAfterDecimal": 2,
        "currencySymbolPosition": "BEFORE_NUMBER"
      },
      "longitude": -72.866821,
      "latitude": 41.604918
    },
    {
      "transactionId": 171365,
      "account": {
        "accountId": 305,
        "accountClosingDate": null,
        "accountOpeningDate": 1184040000000,
        "accountType": {
          "accountTypeId": 16,
          "accountType": "VIRTUAL_WALLET_RESERVE",
          "active": "Y",
          "description": "PNC Virtual Wallet Reserve (Interest Checking)",
          "interestRate": null,
          "annualPercentageRate": null,
          "creditLimit": 6
        },
        "accountNumber": "12488057354529",
        "alterDate": 1184040000000,
        "balance": 1000,
        "businessUnit": {
          "businessUnitId": 1,
          "address": "1736 East Carson Street, Pittsburgh, PA",
          "bank": {
            "bankId": 1,
            "bankName": "PNC",
            "bankRegNumber": "10310080",
            "country": "USA",
            "registeredAddress": "1 PNC Plaza, 249 5th Ave, Pittsburgh, PA 15222",
            "routingNumber": "031000053"
          },
          "unitName": "PNC South Side"
        },
        "isJointAccount": "N",
        "isOnlineAccessEnabled": "Y",
        "status": "ACTIVE",
        "version": 0
      },
      "balance": 1379.5,
      "counterPartyAccount": {
        "accountId": 157,
        "accountClosingDate": null,
        "accountOpeningDate": 1234414800000,
        "accountType": {
          "accountTypeId": 1,
          "accountType": "STANDARD_SAVINGS",
          "active": "Y",
          "description": "Standard Savings",
          "interestRate": 12,
          "annualPercentageRate": 0,
          "creditLimit": 0
        },
        "accountNumber": "14686072495145",
        "alterDate": 1254283200000,
        "balance": 2500,
        "businessUnit": {
          "businessUnitId": 4,
          "address": "5810 Forbes Avenue, Pittsburgh, PA",
          "bank": {
            "bankId": 1,
            "bankName": "PNC",
            "bankRegNumber": "10310080",
            "country": "USA",
            "registeredAddress": "1 PNC Plaza, 249 5th Ave, Pittsburgh, PA 15222",
            "routingNumber": "031000053"
          },
          "unitName": "PNC Squirrel Hill"
        },
        "isJointAccount": "N",
        "isOnlineAccessEnabled": "Y",
        "status": "ACTIVE",
        "version": 2863
      },
      "method": "CREDIT",
      "amount": 25,
      "transactionDate": 1390366800000,
      "transactionType": {
        "transactionTypeId": 1,
        "accountType": "ATM",
        "active": "Y",
        "description": "Deposit or withdraw funds using an ATM."
      },
      "mccCode": {
        "mccCode": 5533,
        "editedDescription": "Automotive Parts, Accessories Stores",
        "combinedDescription": "Automotive Parts, Accessories Stores",
        "usdaDescription": "Automotive Parts, Accessories Stores",
        "irsDescription": "Automotive",
        "irsReportable": "No1.6041-3(c)"
      },
      "comments": "ATM Credit",
      "currency": {
        "currencyCode": "USD",
        "active": "Y",
        "alterDate": 1486875600000,
        "description": "United States Dollar",
        "symbol": "USD",
        "digitsAfterDecimal": 2,
        "currencySymbolPosition": "BEFORE_NUMBER"
      },
      "longitude": -89.390259,
      "latitude": 40.084113
    },
    {
      "transactionId": 171370,
      "account": {
        "accountId": 305,
        "accountClosingDate": null,
        "accountOpeningDate": 1184040000000,
        "accountType": {
          "accountTypeId": 16,
          "accountType": "VIRTUAL_WALLET_RESERVE",
          "active": "Y",
          "description": "PNC Virtual Wallet Reserve (Interest Checking)",
          "interestRate": null,
          "annualPercentageRate": null,
          "creditLimit": 6
        },
        "accountNumber": "12488057354529",
        "alterDate": 1184040000000,
        "balance": 1000,
        "businessUnit": {
          "businessUnitId": 1,
          "address": "1736 East Carson Street, Pittsburgh, PA",
          "bank": {
            "bankId": 1,
            "bankName": "PNC",
            "bankRegNumber": "10310080",
            "country": "USA",
            "registeredAddress": "1 PNC Plaza, 249 5th Ave, Pittsburgh, PA 15222",
            "routingNumber": "031000053"
          },
          "unitName": "PNC South Side"
        },
        "isJointAccount": "N",
        "isOnlineAccessEnabled": "Y",
        "status": "ACTIVE",
        "version": 0
      },
      "balance": 1284.5,
      "counterPartyAccount": {
        "accountId": 354,
        "accountClosingDate": null,
        "accountOpeningDate": 1241928000000,
        "accountType": {
          "accountTypeId": 17,
          "accountType": "VIRTUAL_WALLET_GROWTH",
          "active": "Y",
          "description": "PNC Virtual Wallet Growth (Savings)",
          "interestRate": null,
          "annualPercentageRate": null,
          "creditLimit": 10
        },
        "accountNumber": "25931019747963",
        "alterDate": 1241928000000,
        "balance": 1000,
        "businessUnit": {
          "businessUnitId": 1,
          "address": "1736 East Carson Street, Pittsburgh, PA",
          "bank": {
            "bankId": 1,
            "bankName": "PNC",
            "bankRegNumber": "10310080",
            "country": "USA",
            "registeredAddress": "1 PNC Plaza, 249 5th Ave, Pittsburgh, PA 15222",
            "routingNumber": "031000053"
          },
          "unitName": "PNC South Side"
        },
        "isJointAccount": "N",
        "isOnlineAccessEnabled": "Y",
        "status": "ACTIVE",
        "version": 0
      },
      "method": "DEBIT",
      "amount": 95,
      "transactionDate": 1390539600000,
      "transactionType": {
        "transactionTypeId": 6,
        "accountType": "ONLINE",
        "active": "Y",
        "description": "Withdraw funds through a web-based store or online banking service."
      },
      "mccCode": {
        "mccCode": 5411,
        "editedDescription": "Grocery Stores, Supermarkets",
        "combinedDescription": "Grocery Stores, Supermarkets",
        "usdaDescription": "Grocery Stores",
        "irsDescription": "Groceries",
        "irsReportable": "No1.6041-3(c)"
      },
      "comments": "ONLINE",
      "currency": {
        "currencyCode": "USD",
        "active": "Y",
        "alterDate": 1486875600000,
        "description": "United States Dollar",
        "symbol": "USD",
        "digitsAfterDecimal": 2,
        "currencySymbolPosition": "BEFORE_NUMBER"
      },
      "longitude": -89.390259,
      "latitude": 40.084113
    },
    {
      "transactionId": 171375,
      "account": {
        "accountId": 305,
        "accountClosingDate": null,
        "accountOpeningDate": 1184040000000,
        "accountType": {
          "accountTypeId": 16,
          "accountType": "VIRTUAL_WALLET_RESERVE",
          "active": "Y",
          "description": "PNC Virtual Wallet Reserve (Interest Checking)",
          "interestRate": null,
          "annualPercentageRate": null,
          "creditLimit": 6
        },
        "accountNumber": "12488057354529",
        "alterDate": 1184040000000,
        "balance": 1000,
        "businessUnit": {
          "businessUnitId": 1,
          "address": "1736 East Carson Street, Pittsburgh, PA",
          "bank": {
            "bankId": 1,
            "bankName": "PNC",
            "bankRegNumber": "10310080",
            "country": "USA",
            "registeredAddress": "1 PNC Plaza, 249 5th Ave, Pittsburgh, PA 15222",
            "routingNumber": "031000053"
          },
          "unitName": "PNC South Side"
        },
        "isJointAccount": "N",
        "isOnlineAccessEnabled": "Y",
        "status": "ACTIVE",
        "version": 0
      },
      "balance": 1172.5,
      "counterPartyAccount": {
        "accountId": 691,
        "accountClosingDate": null,
        "accountOpeningDate": 1167973200000,
        "accountType": {
          "accountTypeId": 1,
          "accountType": "STANDARD_SAVINGS",
          "active": "Y",
          "description": "Standard Savings",
          "interestRate": 12,
          "annualPercentageRate": 0,
          "creditLimit": 0
        },
        "accountNumber": "61229063534951",
        "alterDate": 1184040000000,
        "balance": 2500,
        "businessUnit": {
          "businessUnitId": 1,
          "address": "1736 East Carson Street, Pittsburgh, PA",
          "bank": {
            "bankId": 1,
            "bankName": "PNC",
            "bankRegNumber": "10310080",
            "country": "USA",
            "registeredAddress": "1 PNC Plaza, 249 5th Ave, Pittsburgh, PA 15222",
            "routingNumber": "031000053"
          },
          "unitName": "PNC South Side"
        },
        "isJointAccount": "N",
        "isOnlineAccessEnabled": "Y",
        "status": "ACTIVE",
        "version": 2851
      },
      "method": "DEBIT",
      "amount": 112,
      "transactionDate": 1390626000000,
      "transactionType": {
        "transactionTypeId": 1,
        "accountType": "ATM",
        "active": "Y",
        "description": "Deposit or withdraw funds using an ATM."
      },
      "mccCode": {
        "mccCode": 5411,
        "editedDescription": "Grocery Stores, Supermarkets",
        "combinedDescription": "Grocery Stores, Supermarkets",
        "usdaDescription": "Grocery Stores",
        "irsDescription": "Groceries",
        "irsReportable": "No1.6041-3(c)"
      },
      "comments": "ATM Debit",
      "currency": {
        "currencyCode": "USD",
        "active": "Y",
        "alterDate": 1486875600000,
        "description": "United States Dollar",
        "symbol": "USD",
        "digitsAfterDecimal": 2,
        "currencySymbolPosition": "BEFORE_NUMBER"
      },
      "longitude": -75.687561,
      "latitude": 39.120339
    }
  ],
  "last": false,
  "totalPages": 71,
  "totalElements": 703,
  "sort": null,
  "numberOfElements": 10,
  "first": true,
  "size": 10,
  "number": 0
}